<domain type='xen'>
    <name>{{name}}</name>
    <uuid>{{uuid}}</uuid>
  <memory unit='KiB'>{{memory}}</memory>
  <vcpu placement='static'>{{vcpu}}</vcpu>
  <os>
    <type arch='x86_64' machine='xenfv'>hvm</type>
    <loader type='rom'>/usr/lib/xen/boot/hvmloader</loader>
    <boot dev='network'/>
    <boot dev='hd'/>
  </os>
  <features>
    <acpi/>
    <apic/>
    <pae/>
  </features>
  <clock offset='variable' adjustment='0' basis='utc'/>
  <on_poweroff>destroy</on_poweroff>
  <on_reboot>restart</on_reboot>
  <on_crash>restart</on_crash>
  <devices>
    {% for disk, info in disks.items %}
    <disk type='block' device='disk'>
      <driver name='qemu' type='raw'/>
      <source dev='{{disk}}'/>
      <target dev='xvd{{info.0}}' bus='virtio'/>
      <address type='pci' domain='0x0000' bus='0x00' slot='0x04' function='0x0'/>
    </disk>
    {% endfor %}
    {% for net in networks %}
    <interface type='network'>
        <source network='{{net}}'/>
    </interface>
    {% endfor %}
    <input type='mouse' bus='ps2'/>
    <input type='keyboard' bus='ps2'/>
    <graphics type='vnc' port='-1' autoport='yes' listen='0.0.0.0'>
      <listen type='address' address='0.0.0.0'/>
    </graphics>
    <video>
      <model type='cirrus' vram='9216' heads='1'/>
    </video>
  </devices>
</domain>
